[{"name":"Aarna","year":2007,"AK":0.0,"AL":0.0,"AR":0.0,"AZ":0.0,"CA":10.0,"CO":0.0,"CT":0.0,"DC":0.0,"DE":0.0,"FL":0.0,"GA":0.0,"HI":0.0,"IA":0.0,"ID":0.0,"IL":0.0,"IN":0.0,"KS":0.0,"KY":0.0,"LA":0.0,"MA":0.0,"MD":0.0,"ME":0.0,"MI":0.0,"MN":0.0,"MO":0.0,"MS":0.0,"MT":0.0,"NC":0.0,"ND":0.0,"NE":0.0,"NH":0.0,"NJ":0.0,"NM":0.0,"NV":0.0,"NY":0.0,"OH":0.0,"OK":0.0,"OR":0.0,"PA":0.0,"RI":0.0,"SC":0.0,"SD":0.0,"TN":0.0,"TX":0.0,"UT":0.0,"VA":0.0,"VT":0.0,"WA":0.0,"WI":0.0,"WV":0.0,"WY":0.0,"Total":10.0},{"name":"Aarna","year":2008,"AK":0.0,"AL":0.0,"AR":0.0,"AZ":0.0,"CA":10.0,"CO":0.0,"CT":0.0,"DC":0.0,"DE":0.0,"FL":0.0,"GA":0.0,"HI":0.0,"IA":0.0,"ID":0.0,"IL":0.0,"IN":0.0,"KS":0.0,"KY":0.0,"LA":0.0,"MA":0.0,"MD":0.0,"ME":0.0,"MI":0.0,"MN":0.0,"MO":0.0,"MS":0.0,"MT":0.0,"NC":0.0,"ND":0.0,"NE":0.0,"NH":0.0,"NJ":8.0,"NM":0.0,"NV":0.0,"NY":0.0,"OH":0.0,"OK":0.0,"OR":0.0,"PA":0.0,"RI":0.0,"SC":0.0,"SD":0.0,"TN":0.0,"TX":0.0,"UT":0.0,"VA":0.0,"VT":0.0,"WA":0.0,"WI":0.0,"WV":0.0,"WY":0.0,"Total":18.0},{"name":"Aarna","year":2009,"AK":0.0,"AL":0.0,"AR":0.0,"AZ":0.0,"CA":9.0,"CO":0.0,"CT":0.0,"DC":0.0,"DE":0.0,"FL":0.0,"GA":0.0,"HI":0.0,"IA":0.0,"ID":0.0,"IL":0.0,"IN":0.0,"KS":0.0,"KY":0.0,"LA":0.0,"MA":0.0,"MD":0.0,"ME":0.0,"MI":0.0,"MN":0.0,"MO":0.0,"MS":0.0,"MT":0.0,"NC":0.0,"ND":0.0,"NE":0.0,"NH":0.0,"NJ":5.0,"NM":0.0,"NV":0.0,"NY":0.0,"OH":0.0,"OK":0.0,"OR":0.0,"PA":0.0,"RI":0.0,"SC":0.0,"SD":0.0,"TN":0.0,"TX":7.0,"UT":0.0,"VA":0.0,"VT":0.0,"WA":0.0,"WI":0.0,"WV":0.0,"WY":0.0,"Total":21.0},{"name":"Aarna","year":2010,"AK":0.0,"AL":0.0,"AR":0.0,"AZ":0.0,"CA":16.0,"CO":0.0,"CT":9.0,"DC":0.0,"DE":0.0,"FL":8.0,"GA":0.0,"HI":0.0,"IA":0.0,"ID":0.0,"IL":0.0,"IN":0.0,"KS":0.0,"KY":0.0,"LA":0.0,"MA":0.0,"MD":0.0,"ME":0.0,"MI":0.0,"MN":0.0,"MO":0.0,"MS":0.0,"MT":0.0,"NC":6.0,"ND":0.0,"NE":0.0,"NH":0.0,"NJ":14.0,"NM":0.0,"NV":0.0,"NY":0.0,"OH":0.0,"OK":0.0,"OR":0.0,"PA":0.0,"RI":0.0,"SC":0.0,"SD":0.0,"TN":0.0,"TX":7.0,"UT":0.0,"VA":0.0,"VT":0.0,"WA":0.0,"WI":0.0,"WV":0.0,"WY":0.0,"Total":60.0},{"name":"Aarna","year":2011,"AK":0.0,"AL":0.0,"AR":0.0,"AZ":0.0,"CA":28.0,"CO":0.0,"CT":5.0,"DC":0.0,"DE":0.0,"FL":0.0,"GA":6.0,"HI":0.0,"IA":0.0,"ID":0.0,"IL":6.0,"IN":0.0,"KS":0.0,"KY":0.0,"LA":0.0,"MA":0.0,"MD":0.0,"ME":0.0,"MI":0.0,"MN":0.0,"MO":0.0,"MS":0.0,"MT":0.0,"NC":0.0,"ND":0.0,"NE":0.0,"NH":0.0,"NJ":17.0,"NM":0.0,"NV":0.0,"NY":0.0,"OH":0.0,"OK":0.0,"OR":0.0,"PA":0.0,"RI":0.0,"SC":0.0,"SD":0.0,"TN":0.0,"TX":8.0,"UT":0.0,"VA":9.0,"VT":0.0,"WA":0.0,"WI":0.0,"WV":0.0,"WY":0.0,"Total":79.0},{"name":"Aarna","year":2012,"AK":0.0,"AL":0.0,"AR":0.0,"AZ":0.0,"CA":22.0,"CO":0.0,"CT":0.0,"DC":0.0,"DE":0.0,"FL":0.0,"GA":6.0,"HI":0.0,"IA":0.0,"ID":0.0,"IL":0.0,"IN":0.0,"KS":0.0,"KY":0.0,"LA":0.0,"MA":7.0,"MD":0.0,"ME":0.0,"MI":0.0,"MN":0.0,"MO":0.0,"MS":0.0,"MT":0.0,"NC":7.0,"ND":0.0,"NE":0.0,"NH":0.0,"NJ":15.0,"NM":0.0,"NV":0.0,"NY":0.0,"OH":0.0,"OK":0.0,"OR":0.0,"PA":8.0,"RI":0.0,"SC":0.0,"SD":0.0,"TN":0.0,"TX":9.0,"UT":0.0,"VA":7.0,"VT":0.0,"WA":0.0,"WI":0.0,"WV":0.0,"WY":0.0,"Total":81.0},{"name":"Aarna","year":2013,"AK":0.0,"AL":6.0,"AR":0.0,"AZ":0.0,"CA":20.0,"CO":0.0,"CT":0.0,"DC":0.0,"DE":0.0,"FL":0.0,"GA":8.0,"HI":0.0,"IA":0.0,"ID":0.0,"IL":9.0,"IN":0.0,"KS":0.0,"KY":0.0,"LA":0.0,"MA":0.0,"MD":0.0,"ME":0.0,"MI":0.0,"MN":0.0,"MO":0.0,"MS":0.0,"MT":0.0,"NC":6.0,"ND":0.0,"NE":0.0,"NH":0.0,"NJ":18.0,"NM":0.0,"NV":0.0,"NY":0.0,"OH":0.0,"OK":0.0,"OR":0.0,"PA":9.0,"RI":0.0,"SC":0.0,"SD":0.0,"TN":0.0,"TX":12.0,"UT":0.0,"VA":10.0,"VT":0.0,"WA":0.0,"WI":0.0,"WV":0.0,"WY":0.0,"Total":98.0},{"name":"Aarna","year":2014,"AK":0.0,"AL":0.0,"AR":0.0,"AZ":5.0,"CA":35.0,"CO":0.0,"CT":0.0,"DC":0.0,"DE":0.0,"FL":0.0,"GA":5.0,"HI":0.0,"IA":0.0,"ID":0.0,"IL":13.0,"IN":0.0,"KS":0.0,"KY":0.0,"LA":0.0,"MA":0.0,"MD":0.0,"ME":0.0,"MI":7.0,"MN":0.0,"MO":0.0,"MS":0.0,"MT":0.0,"NC":5.0,"ND":0.0,"NE":0.0,"NH":0.0,"NJ":18.0,"NM":0.0,"NV":0.0,"NY":5.0,"OH":0.0,"OK":0.0,"OR":0.0,"PA":12.0,"RI":0.0,"SC":0.0,"SD":0.0,"TN":0.0,"TX":22.0,"UT":0.0,"VA":6.0,"VT":0.0,"WA":6.0,"WI":0.0,"WV":0.0,"WY":0.0,"Total":139.0},{"name":"Aarna","year":2015,"AK":0.0,"AL":0.0,"AR":0.0,"AZ":0.0,"CA":24.0,"CO":0.0,"CT":0.0,"DC":0.0,"DE":0.0,"FL":0.0,"GA":5.0,"HI":0.0,"IA":0.0,"ID":0.0,"IL":15.0,"IN":0.0,"KS":0.0,"KY":0.0,"LA":0.0,"MA":5.0,"MD":0.0,"ME":0.0,"MI":0.0,"MN":0.0,"MO":0.0,"MS":0.0,"MT":0.0,"NC":7.0,"ND":0.0,"NE":0.0,"NH":0.0,"NJ":22.0,"NM":0.0,"NV":0.0,"NY":0.0,"OH":5.0,"OK":0.0,"OR":0.0,"PA":5.0,"RI":0.0,"SC":0.0,"SD":0.0,"TN":0.0,"TX":12.0,"UT":0.0,"VA":7.0,"VT":0.0,"WA":5.0,"WI":0.0,"WV":0.0,"WY":0.0,"Total":112.0}]